erddapcfg/__init__.py
erddapcfg/classes.py
erddapcfg/cli.py
erddapcfg/db_to_obj.py
erddapcfg/db_to_xml.py
erddapcfg/obj_to_db.py
erddapcfg/obj_to_sql.py
erddapcfg/obj_to_xml.py
erddapcfg/sql_script.py
erddapcfg/template_utils.py
erddapcfg/utils.py
erddapcfg/xml_to_db.py
erddapcfg/xml_to_obj.py
erddapcfg/xml_to_sql.py
erddapcfg/templates/datasets.xml.j2
erddapcfg/templates/db_insert.j2
erddapcfg/templates/macro.j2
erddapcfg-0.0.2.data/data/datasets.xml.j2
erddapcfg-0.0.2.data/data/db_insert.j2
erddapcfg-0.0.2.data/data/macro.j2
erddapcfg-0.0.2.dist-info/LICENSE
erddapcfg-0.0.2.dist-info/METADATA
erddapcfg-0.0.2.dist-info/WHEEL
erddapcfg-0.0.2.dist-info/entry_points.txt
erddapcfg-0.0.2.dist-info/top_level.txt
erddapcfg-0.0.2.dist-info/RECORD
