Metadata-Version: 2.1
Name: erddapcfg
Version: 0.0.2
Summary: Python program to work with ERDDAP configurations.
Home-page: https://github.com/PlehanSebastian/erddapcfg
Author: Sebastian Plehan
Author-email: plehan.sebastian@gmail.com
License-File: LICENSE
Requires-Dist: pandas
Requires-Dist: jinja2
